reflex_intersection_observer/__init__.py
reflex_intersection_observer/intersection_observer.py
reflex_intersection_observer-0.0.6.dist-info/METADATA
reflex_intersection_observer-0.0.6.dist-info/WHEEL
reflex_intersection_observer-0.0.6.dist-info/top_level.txt
reflex_intersection_observer-0.0.6.dist-info/RECORD
