Metadata-Version: 2.2
Name: reflex-intersection-observer
Version: 0.0.6
Summary: Reflex custom component intersection-observer
Author-email: Masen Furer <m_github@0x26.net>
License: Apache-2.0
Project-URL: Homepage, https://github.com/masenf/reflex-intersection-observer
Keywords: reflex,reflex-custom-components
Classifier: Development Status :: 4 - Beta
Requires-Python: >=3.10
Requires-Dist: jinja2>=3.1.2
Requires-Dist: reflex>=0.6.6
Provides-Extra: dev
Requires-Dist: build; extra == "dev"
Requires-Dist: twine; extra == "dev"
